flaskdrop/__init__.py
flaskdrop/__main__.py
flaskdrop-0.0.3.dist-info/METADATA
flaskdrop-0.0.3.dist-info/WHEEL
flaskdrop-0.0.3.dist-info/top_level.txt
flaskdrop-0.0.3.dist-info/RECORD
