Metadata-Version: 2.1
Name: flaskdrop
Version: 0.0.3
Summary: A small http file drop server
Home-page: https://github.com/bouni/flaskdrop
Author: Bouni
Author-email: bouni-flaskdrop@owee.de
License: UNKNOWN
Project-URL: Bug Tracker, https://github.com/bouni/flaskdrop/issues
Platform: UNKNOWN
Classifier: Programming Language :: Python :: 3
Classifier: License :: OSI Approved :: MIT License
Classifier: Operating System :: OS Independent
Requires-Python: >=3.9
Requires-Dist: flask (>=2.1.1)
